latencyai/__init__.py
latencyai/__main__.py
latencyai/benchmark_main.py
latencyai/benchmark_runner.py
latencyai/openai_chat.py
latencyai-0.1.1.dist-info/LICENSE
latencyai-0.1.1.dist-info/METADATA
latencyai-0.1.1.dist-info/WHEEL
latencyai-0.1.1.dist-info/entry_points.txt
latencyai-0.1.1.dist-info/RECORD
