Metadata-Version: 2.3
Name: latencyai
Version: 0.1.1
Summary: AI Performance Engineer
License: MIT
Keywords: Performance engineering,Performance tuning
Author: Graphsignal, Inc.
Author-email: devops@graphsignal.com
Requires-Python: >=3.9
Classifier: Development Status :: 5 - Production/Stable
Classifier: Intended Audience :: Developers
Classifier: Intended Audience :: Science/Research
Classifier: License :: OSI Approved :: Apache Software License
Classifier: License :: OSI Approved :: MIT License
Classifier: Operating System :: OS Independent
Classifier: Programming Language :: Python
Classifier: Programming Language :: Python :: 3
Classifier: Programming Language :: Python :: 3.9
Classifier: Programming Language :: Python :: 3.10
Classifier: Programming Language :: Python :: 3.11
Classifier: Programming Language :: Python :: 3.12
Classifier: Programming Language :: Python :: 3.13
Classifier: Topic :: Scientific/Engineering
Classifier: Topic :: Scientific/Engineering :: Artificial Intelligence
Classifier: Topic :: Software Development
Classifier: Topic :: System :: Monitoring
Requires-Dist: numpy
Requires-Dist: openai
Requires-Dist: pydantic (>2)
Requires-Dist: python-dateutil
Requires-Dist: torch
Requires-Dist: typing-extensions (>4.7.1)
Project-URL: Homepage, https://graphsignal.com
Project-URL: Repository, https://graphsignal.com
